{
  "tsserver.implicitProjectConfig.experimentalDecorators": true,
  "javascript.suggestionActions.enabled": false,
  "eslint.packageManager": "yarn",
  "tsserver.tsdk": "node_modules/typescript/lib",
  "python.formatting.provider": "black",
  "Lua.diagnostics.globals": ["vim"],
  "languageserver": {
    "terraform": {
      "command": "terraform-ls",
      "args": ["serve"],
      "filetypes": ["terraform", "tf"],
      "initializationOptions": {},
      "settings": {}
    }
  },
  "list.floatPreview": true,
  "list.height": 16,
  "list.maxPreviewHeight": 24
}
